myers_diff/__init__.py
myers_diff/main.c
myers_diff/myers.c
myers_diff/myers.h
myers_diff/myers_wrapper.c
myers_diff/myers_wrapper.cpython-312-darwin.so
myers_diff/myers_wrapper.pyx
myers_diff/setup.py
myers_diff/test_myers.py
myers_diff-0.1.0.dist-info/licenses/LICENSE
myers_diff-0.1.0.dist-info/METADATA
myers_diff-0.1.0.dist-info/WHEEL
myers_diff-0.1.0.dist-info/top_level.txt
myers_diff-0.1.0.dist-info/RECORD
