Metadata-Version: 2.4
Name: myers-diff
Version: 0.1.0
Summary: High-performance Myers diff algorithm in C with Python bindings
Author-email: Your Name <your.email@example.com>
License: MIT
Project-URL: Homepage, https://github.com/yourusername/myers-diff
Project-URL: Repository, https://github.com/yourusername/myers-diff
Keywords: diff,myers,edit-distance,lcs,algorithm
Classifier: Development Status :: 4 - Beta
Classifier: Intended Audience :: Developers
Classifier: License :: OSI Approved :: MIT License
Classifier: Programming Language :: Python :: 3
Classifier: Programming Language :: Python :: 3.8
Classifier: Programming Language :: Python :: 3.9
Classifier: Programming Language :: Python :: 3.10
Classifier: Programming Language :: Python :: 3.11
Classifier: Programming Language :: Python :: 3.12
Classifier: Programming Language :: C
Classifier: Topic :: Software Development :: Libraries :: Python Modules
Classifier: Topic :: Text Processing :: General
Requires-Python: >=3.8
License-File: LICENSE
Dynamic: license-file
